{
  "replies": {
    "warmup": [
      "你好，我们先从你的项目经历开始。请你用两分钟介绍一下你在校园面试模拟平台中负责的核心工作。",
      "你刚才提到了简历解析和会话记录，先说说你为什么这样拆分模块，以及这样拆分带来的好处。"
    ],
    "technical": [
      "进入技术阶段。请你结合 Spring Boot 项目，说明一次完整请求从 Controller 到数据库落库的调用链，以及你在哪些位置做了异常处理。",
      "如果简历管理列表在高并发场景下访问量上升，你会优先从数据库、缓存还是接口层做优化？请给出你的判断依据。"
    ],
    "deep_dive": [
      "继续深挖。你在项目里用到了流式 SSE，如果客户端中途断开连接，后端如何保证资源释放与状态一致？",
      "如果用户在切换面试阶段时出现重复提交，你会如何保证阶段推进的幂等性和顺序正确？"
    ],
    "closing": [
      "最后一个问题。如果让你继续完善这个系统，你会优先补哪一块能力，为什么？"
    ]
  }
}
